setup.py
ResponsiveVoice.egg-info/PKG-INFO
ResponsiveVoice.egg-info/SOURCES.txt
ResponsiveVoice.egg-info/dependency_links.txt
ResponsiveVoice.egg-info/requires.txt
ResponsiveVoice.egg-info/top_level.txt
responsive_voice/__init__.py
responsive_voice/voices.py