Metadata-Version: 1.0
Name: ResponsiveVoice
Version: 0.4.2
Summary: unofficial python wrapper for responsive voice
Home-page: https://github.com/OpenJarbas/py_responsivevoice
Author: jarbasAI
Author-email: jarbasai@mailfence.com
License: Apache2
Platform: UNKNOWN
